diffusion_prompt_embedder/__init__.py
diffusion_prompt_embedder/py.typed
diffusion_prompt_embedder/clip/__init__.py
diffusion_prompt_embedder/clip/tokenization.py
diffusion_prompt_embedder/core/__init__.py
diffusion_prompt_embedder/core/embedding.py
diffusion_prompt_embedder/core/parser.py
diffusion_prompt_embedder-0.2.0.dist-info/METADATA
diffusion_prompt_embedder-0.2.0.dist-info/WHEEL
diffusion_prompt_embedder-0.2.0.dist-info/RECORD
