Metadata-Version: 2.4
Name: diffusion-prompt-embedder
Version: 0.2.0
Summary: A Python library for parsing and processing prompts with support for embedding and tokenization.
Project-URL: Homepage, https://github.com/jannchie/diffusion-prompt-embedder
Project-URL: Bug Tracker, https://github.com/jannchie/diffusion-prompt-embedder/issues
Project-URL: Documentation, https://github.com/jannchie/diffusion-prompt-embedder#readme
Author-email: Jianqi Pan <jannchie@gmail.com>
License: MIT
Keywords: ai,embedding,nlp,prompt,stable diffusion,tokenization
Classifier: Development Status :: 4 - Beta
Classifier: Intended Audience :: Developers
Classifier: License :: OSI Approved :: MIT License
Classifier: Programming Language :: Python :: 3
Classifier: Programming Language :: Python :: 3.10
Classifier: Programming Language :: Python :: 3.11
Classifier: Programming Language :: Python :: 3.12
Classifier: Programming Language :: Python :: 3.13
Classifier: Programming Language :: Python :: 3.14
Classifier: Topic :: Scientific/Engineering :: Artificial Intelligence
Requires-Python: >=3.10
Provides-Extra: all
Requires-Dist: torch>=2.0.0; extra == 'all'
Requires-Dist: transformers>=4.51.3; extra == 'all'
Provides-Extra: dev
Requires-Dist: pytest-cov>=6.1.1; extra == 'dev'
Requires-Dist: pytest>=8.3.5; extra == 'dev'
Requires-Dist: torch>=2.0.0; extra == 'dev'
Requires-Dist: transformers>=4.51.3; extra == 'dev'
Provides-Extra: torch
Requires-Dist: torch>=2.0.0; extra == 'torch'
Provides-Extra: transformers
Requires-Dist: transformers>=4.51.3; extra == 'transformers'
